mamba_paw-0.3.1.dist-info/DESCRIPTION.rst
mamba_paw-0.3.1.dist-info/METADATA
mamba_paw-0.3.1.dist-info/RECORD
mamba_paw-0.3.1.dist-info/WHEEL
mamba_paw-0.3.1.dist-info/metadata.json
mamba_paw-0.3.1.dist-info/top_level.txt
paw/__init__.py
paw/exceptions.py
paw/models.py
paw/utils.py
