Metadata-Version: 2.0
Name: mamba-paw
Version: 0.3.1
Summary: Uses Azure storage queue/table for a simple worker
Home-page: https://github.com/ayudasystems/mamba-paw
Author: Maxime Lapointe
Author-email: maxime@ayudasystems.com
License: Apache 2.0
Platform: UNKNOWN
Classifier: Development Status :: 3 - Alpha
Classifier: Intended Audience :: Developers
Classifier: Topic :: Software Development
Classifier: Programming Language :: Python :: 3.5
Classifier: Programming Language :: Python :: 3.6
Requires-Python: >=3.5
Requires-Dist: azure-storage (>==0.36.0)
